{
  "diseaseId": "transtorno-bipolar",
  "region": "EU",
  "diseaseName": "Bipolar Disorder",
  "prevalence": {
    "value": "1-2%",
    "population": "EU adults (~447 million)",
    "year": 2024,
    "source": "WHO Europe / European psychiatric epidemiology syntheses",
    "trend": "stable; diagnosis and maintenance care improving"
  },
  "incidence": {
    "value": "1-3 per 1,000/year",
    "population": "EU adults",
    "year": 2024,
    "source": "European cohort syntheses"
  },
  "burden": {
    "dalyPerCapita": "0.01-0.03",
    "mortalityRate": "Indirect; elevated suicide and comorbidity risk",
    "year": 2024,
    "source": "IHME GBD / WHO Europe"
  },
  "epidemiology": {
    "riskFactors": [
      "family history",
      "sleep disruption",
      "substance use",
      "stressful life events"
    ],
    "vulnerablePopulations": [
      "young adults",
      "people with substance use disorders",
      "patients with recurrent depression (misdiagnosis risk)"
    ],
    "diagnosticCriteria": "DSM-5/ICD-11 criteria; structured assessment in specialist care; emphasis on distinguishing bipolar vs unipolar depression"
  },
  "publicHealthSystem": {
    "screeningCoverage": "moderate; specialist referral pathways common",
    "treatmentAvailable": true,
    "estimatedPatients": "~5-8 million",
    "controlRate": "Moderate to high with maintenance therapy and psychosocial support; varies by country"
  },
  "regionalSpecificities": {
    "diagnosisCriteria": "Access to psychiatric assessment and monitoring is generally high in many member states",
    "treatmentProtocol": "Mood stabilizers (lithium, valproate, lamotrigine) and atypical antipsychotics; structured relapse prevention and psychoeducation",
    "regionalChallenges": "Therapy access variability and comorbid substance use management",
    "strongPoints": "Robust specialist care and monitoring capacity, with established maintenance pathways"
  }
}

